{
    "[不常]": [
        "那請問一下，您的孩子有時會不會像小鸚鵡那樣，重複您說的帶有三個語言的句子呢？例如：玩具放進箱子、是誰來了...等這樣長度的句子？"
    ],
    "不[一定]": [
        "那請問一下，您的孩子有時會不會像小鸚鵡那樣，重複您說的帶有三個語言的句子呢？例如：玩具放進箱子、是誰來了...等這樣長度的句子？"
    ],
    "不太[會]": [
        "那請問一下，您的孩子有時會不會像小鸚鵡那樣，重複您說的帶有三個語言的句子呢？例如：玩具放進箱子、是誰來了...等這樣長度的句子？"
    ],
    "不太行": [
        "那請問一下，您的孩子有時會不會像小鸚鵡那樣，重複您說的帶有三個語言的句子呢？例如：玩具放進箱子、是誰來了...等這樣長度的句子？"
    ],
    "很少": [
        "那請問一下，您的孩子有時會不會像小鸚鵡那樣，重複您說的帶有三個語言的句子呢？例如：玩具放進箱子、是誰來了...等這樣長度的句子？"
    ],
    "看[心情]": [
        "那請問一下，您的孩子有時會不會像小鸚鵡那樣，重複您說的帶有三個語言的句子呢？例如：玩具放進箱子、是誰來了...等這樣長度的句子？"
    ],
    "要看說什麼": [
        "那請問一下，您的孩子有時會不會像小鸚鵡那樣，重複您說的帶有三個語言的句子呢？例如：玩具放進箱子、是誰來了...等這樣長度的句子？"
    ]
}