{
    "[不太]確定": [
        "這樣子呀~那當您和孩子一起玩一些小遊戲時，如：捏手手、玩炒蘿蔔，孩子會動動他的手指或是把手伸到您面前呀？",
        "那...如果在和孩子玩一些互動遊戲時，像是玩炒蘿蔔，他會主動伸出手來嗎？"
    ],
    "不[一定]": [
        "這樣子呀~在您和孩子一起玩的時候，孩子有時會動動他的手指好像要一起玩的樣子嗎？",
        "原來如此，在和孩子互動時，您有看過孩子曾主動伸出手來表示想一起玩的反應嗎？"
    ],
    "不太[會]": [
        "這樣子呀~孩子是否會在和您一起玩一些小遊戲，比如捏手手，他會動動手指，或者把手伸到您面前呢？",
        "是哦...那在您和孩子互動時，有看過孩子曾主動伸出手來表示想一起玩的反應嗎？"
    ],
    "不太理人": [
        "這樣子呀~如果您和孩子一起玩炒蘿蔔時，孩子會動動他的手指或是把手伸到您面前呀？",
        "了解...在日常生活中，當您和孩子一起玩時，孩子是否會有動動手或伸出手來表示想玩呢？"
    ],
    "沒[什麼]反應": [
        "這樣子呀~如果您和孩子玩他喜歡的遊戲時，他會不會動動他的手指或是把手伸到您面前呀？",
        "是哦...如果您或家人跟孩子玩的時候，是否看過孩子動動他的手或舉手表示想要玩呢？"
    ],
    "看[心情]": [
        "這樣子呀~那當孩子心情還不錯時，您和他一起玩玩炒蘿蔔這種小遊戲時，孩子會動動他的手指或是把手伸到您面前呀？",
        "那...如果您和孩子玩他喜歡的遊戲時，他會不會動動他的手指或是把手伸到您面前呀？"
    ],
    "看玩什麼": [
        "這樣子呀~那如果是玩孩子喜歡的遊戲呢，他會不會動動手或是把手伸到您面前表示想一起玩呀？",
        "是哦，那...如果您和孩子玩一些小遊戲，是否看過孩子動動他的手或舉手表示想要玩呢？"
    ]
}